securenative/__init__.py
securenative/api_manager.py
securenative/event_manager.py
securenative/logger.py
securenative/securenative.py
securenative/config/__init__.py
securenative/config/configuration_manager.py
securenative/config/securenative_options.py
securenative/context/__init__.py
securenative/context/securenative_context.py
securenative/enums/__init__.py
securenative/enums/api_route.py
securenative/enums/event_types.py
securenative/enums/failover_strategy.py
securenative/enums/risk_level.py
securenative/exceptions/__init__.py
securenative/exceptions/securenative_config_exception.py
securenative/exceptions/securenative_http_exception.py
securenative/exceptions/securenative_invalid_options_exception.py
securenative/exceptions/securenative_invalid_uri_exception.py
securenative/exceptions/securenative_parse_exception.py
securenative/exceptions/securenative_sdk_Illegal_state_exception.py
securenative/exceptions/securenative_sdk_exception.py
securenative/http/__init__.py
securenative/http/http_response.py
securenative/http/securenative_http_client.py
securenative/models/__init__.py
securenative/models/client_token.py
securenative/models/device.py
securenative/models/event_options.py
securenative/models/request_context.py
securenative/models/request_options.py
securenative/models/sdk_event.py
securenative/models/user_traits.py
securenative/models/verify_result.py
securenative/utils/__init__.py
securenative/utils/date_utils.py
securenative/utils/encryption_utils.py
securenative/utils/ip_utils.py
securenative/utils/request_utils.py
securenative/utils/signature_utils.py
securenative/utils/utils.py
securenative/utils/version_utils.py
tests/__init__.py
tests/api_manager_test.py
tests/configuration_manager_test.py
tests/context_builder_test.py
tests/date_utils_test.py
tests/encryption_utils_test.py
tests/event_manager_test.py
tests/ip_utils_test.py
tests/request_utils_test.py
tests/sdk_event_test.py
tests/securenative_http_client_test.py
tests/securenative_test.py
securenative-0.3.7.dist-info/LICENSE
securenative-0.3.7.dist-info/LICENSE.txt
securenative-0.3.7.dist-info/METADATA
securenative-0.3.7.dist-info/WHEEL
securenative-0.3.7.dist-info/top_level.txt
securenative-0.3.7.dist-info/RECORD
