Metadata-Version: 2.1
Name: securenative
Version: 0.3.7
Summary: Secure Native SDK for python
Home-page: http://www.securenative.com
Author: SecureNative
Author-email: support@securenative.com
License: MIT
Download-URL: https://github.com/securenative/securenative-python/archive/0.1.tar.gz
Keywords: securenative,cyber-security
Platform: UNKNOWN
Classifier: Development Status :: 5 - Production/Stable
Classifier: Intended Audience :: Developers
Classifier: Topic :: Software Development :: Build Tools
Classifier: License :: OSI Approved :: MIT License
Classifier: Programming Language :: Python :: 3
Classifier: Programming Language :: Python :: 3.4
Classifier: Programming Language :: Python :: 3.5
Classifier: Programming Language :: Python :: 3.6
Requires-Dist: requests
Requires-Dist: pycryptodome
